{
  "version": 1,
  "lastUpdated": "2026-05-26",
  "country": "AT",
  "institutions": [
    {
      "code": "CENBAT",
      "name": "Central Bank of AT",
      "shortName": "Central Bank",
      "type": "bank",
      "aliases": ""
    },
    {
      "code": "NATBAT",
      "name": "National Bank of AT",
      "shortName": "National Bank",
      "type": "bank",
      "aliases": ""
    },
    {
      "code": "STABAT",
      "name": "State Bank of AT",
      "shortName": "State Bank",
      "type": "bank",
      "aliases": ""
    },
    {
      "code": "COBBAT",
      "name": "Commercial Bank of AT",
      "shortName": "Commercial Bank",
      "type": "bank",
      "aliases": ""
    },
    {
      "code": "FIBAT",
      "name": "First AT Bank",
      "shortName": "First Bank",
      "type": "bank",
      "aliases": ""
    }
  ]
}