{
  "version": 1,
  "lastUpdated": "2026-05-26",
  "country": "BF",
  "institutions": [
    {
      "code": "CENBBF",
      "name": "Central Bank of BF",
      "shortName": "Central Bank",
      "type": "bank",
      "aliases": ""
    },
    {
      "code": "NATBBF",
      "name": "National Bank of BF",
      "shortName": "National Bank",
      "type": "bank",
      "aliases": ""
    },
    {
      "code": "STABBF",
      "name": "State Bank of BF",
      "shortName": "State Bank",
      "type": "bank",
      "aliases": ""
    },
    {
      "code": "COBBBF",
      "name": "Commercial Bank of BF",
      "shortName": "Commercial Bank",
      "type": "bank",
      "aliases": ""
    },
    {
      "code": "FIBBF",
      "name": "First BF Bank",
      "shortName": "First Bank",
      "type": "bank",
      "aliases": ""
    }
  ]
}