{
  "version": 1,
  "lastUpdated": "2026-05-30",
  "country": "CN",
  "institutions": [
    {
      "code": "CN_0",
      "name": "Agricultural Bank of China",
      "shortName": "Agricultural of Chin",
      "type": "bank",
      "aliases": "ABC"
    },
    {
      "code": "CN_1",
      "name": "Bank of Beijing",
      "shortName": "Bank of Beijing",
      "type": "bank",
      "aliases": ""
    },
    {
      "code": "CN_2",
      "name": "Bank of China",
      "shortName": "Bank of China",
      "type": "bank",
      "aliases": "BOC"
    },
    {
      "code": "CN_3",
      "name": "Bank of Communications",
      "shortName": "Bank of Communicatio",
      "type": "bank",
      "aliases": "BOCOM"
    },
    {
      "code": "CN_4",
      "name": "Bank of Jiangsu",
      "shortName": "Bank of Jiangsu",
      "type": "bank",
      "aliases": ""
    },
    {
      "code": "CN_5",
      "name": "Bank of Ningbo",
      "shortName": "Bank of Ningbo",
      "type": "bank",
      "aliases": ""
    },
    {
      "code": "CN_6",
      "name": "Bank of Shanghai",
      "shortName": "Bank of Shanghai",
      "type": "bank",
      "aliases": ""
    },
    {
      "code": "CN_7",
      "name": "China Construction Bank",
      "shortName": "China Construction",
      "type": "bank",
      "aliases": "CCB"
    },
    {
      "code": "CN_8",
      "name": "China CITIC Bank",
      "shortName": "China CITIC",
      "type": "bank",
      "aliases": ""
    },
    {
      "code": "CN_9",
      "name": "China Everbright Bank",
      "shortName": "China Everbright",
      "type": "bank",
      "aliases": "CEB"
    },
    {
      "code": "CN_10",
      "name": "China Merchants Bank",
      "shortName": "China Merchants",
      "type": "bank",
      "aliases": "CMB"
    },
    {
      "code": "CN_11",
      "name": "China Minsheng Bank",
      "shortName": "China Minsheng",
      "type": "bank",
      "aliases": ""
    },
    {
      "code": "CN_12",
      "name": "Guangdong Development Bank",
      "shortName": "Guangdong Developmen",
      "type": "bank",
      "aliases": "CGB / Guangfa"
    },
    {
      "code": "CN_13",
      "name": "Huaxia Bank",
      "shortName": "Huaxia",
      "type": "bank",
      "aliases": ""
    },
    {
      "code": "CN_14",
      "name": "Industrial and Commercial Bank of China",
      "shortName": "Industrial and Comme",
      "type": "bank",
      "aliases": "ICBC"
    },
    {
      "code": "CN_15",
      "name": "Industrial Bank",
      "shortName": "Industrial",
      "type": "bank",
      "aliases": "CIB"
    },
    {
      "code": "CN_16",
      "name": "Ping An Bank",
      "shortName": "Ping An",
      "type": "bank",
      "aliases": ""
    },
    {
      "code": "CN_17",
      "name": "Postal Savings Bank of China",
      "shortName": "Postal Savings of Ch",
      "type": "bank",
      "aliases": "PSBC"
    },
    {
      "code": "CN_18",
      "name": "Shanghai Pudong Development Bank",
      "shortName": "Shanghai Pudong Deve",
      "type": "bank",
      "aliases": "SPD Bank"
    },
    {
      "code": "CN_19",
      "name": "Alipay",
      "shortName": "Alipay",
      "type": "mfs",
      "aliases": ""
    },
    {
      "code": "CN_20",
      "name": "BestPay",
      "shortName": "BestPay",
      "type": "mfs",
      "aliases": ""
    },
    {
      "code": "CN_21",
      "name": "Cloud Flash Pay",
      "shortName": "Cloud Flash Pay",
      "type": "mfs",
      "aliases": ""
    },
    {
      "code": "CN_22",
      "name": "WeChat Pay",
      "shortName": "WeChat Pay",
      "type": "mfs",
      "aliases": ""
    }
  ]
}