{
  "version": 1,
  "lastUpdated": "2026-05-26",
  "country": "GF",
  "institutions": [
    {
      "code": "CENBGF",
      "name": "Central Bank of GF",
      "shortName": "Central Bank",
      "type": "bank",
      "aliases": ""
    },
    {
      "code": "NATBGF",
      "name": "National Bank of GF",
      "shortName": "National Bank",
      "type": "bank",
      "aliases": ""
    },
    {
      "code": "STABGF",
      "name": "State Bank of GF",
      "shortName": "State Bank",
      "type": "bank",
      "aliases": ""
    },
    {
      "code": "COBBGF",
      "name": "Commercial Bank of GF",
      "shortName": "Commercial Bank",
      "type": "bank",
      "aliases": ""
    },
    {
      "code": "FIBGF",
      "name": "First GF Bank",
      "shortName": "First Bank",
      "type": "bank",
      "aliases": ""
    }
  ]
}