{
  "version": 1,
  "lastUpdated": "2026-05-30",
  "country": "MX",
  "institutions": [
    {
      "code": "MX_0",
      "name": "Afirme",
      "shortName": "Afirme",
      "type": "bank",
      "aliases": ""
    },
    {
      "code": "MX_1",
      "name": "Banco Azteca",
      "shortName": "Azteca",
      "type": "bank",
      "aliases": ""
    },
    {
      "code": "MX_2",
      "name": "Banco del Bajío",
      "shortName": "del Bajío",
      "type": "bank",
      "aliases": "BanBajío"
    },
    {
      "code": "MX_3",
      "name": "Banco Inbursa",
      "shortName": "Inbursa",
      "type": "bank",
      "aliases": ""
    },
    {
      "code": "MX_4",
      "name": "Banco Santander México",
      "shortName": "Santander México",
      "type": "bank",
      "aliases": ""
    },
    {
      "code": "MX_5",
      "name": "BanCoppel",
      "shortName": "BanCoppel",
      "type": "bank",
      "aliases": ""
    },
    {
      "code": "MX_6",
      "name": "Banorte",
      "shortName": "Banorte",
      "type": "bank",
      "aliases": "Banco Mercantil del Norte"
    },
    {
      "code": "MX_7",
      "name": "Banregio",
      "shortName": "Banregio",
      "type": "bank",
      "aliases": ""
    },
    {
      "code": "MX_8",
      "name": "BBVA México",
      "shortName": "BBVA México",
      "type": "bank",
      "aliases": ""
    },
    {
      "code": "MX_9",
      "name": "Bineo",
      "shortName": "Bineo",
      "type": "bank",
      "aliases": ""
    },
    {
      "code": "MX_10",
      "name": "Citibanamex",
      "shortName": "Citibanamex",
      "type": "bank",
      "aliases": "Banco Nacional de México"
    },
    {
      "code": "MX_11",
      "name": "HSBC México",
      "shortName": "HSBC México",
      "type": "bank",
      "aliases": ""
    },
    {
      "code": "MX_12",
      "name": "Mifel",
      "shortName": "Mifel",
      "type": "bank",
      "aliases": ""
    },
    {
      "code": "MX_13",
      "name": "Nu México",
      "shortName": "Nu México",
      "type": "bank",
      "aliases": ""
    },
    {
      "code": "MX_14",
      "name": "Openbank México",
      "shortName": "Openbank México",
      "type": "bank",
      "aliases": ""
    },
    {
      "code": "MX_15",
      "name": "Revolut Bank México",
      "shortName": "Revolut México",
      "type": "bank",
      "aliases": ""
    },
    {
      "code": "MX_16",
      "name": "Scotiabank México",
      "shortName": "Scotiabank México",
      "type": "bank",
      "aliases": ""
    },
    {
      "code": "MX_17",
      "name": "Albo",
      "shortName": "Albo",
      "type": "mfs",
      "aliases": ""
    },
    {
      "code": "MX_18",
      "name": "Broxel",
      "shortName": "Broxel",
      "type": "mfs",
      "aliases": ""
    },
    {
      "code": "MX_19",
      "name": "Fondeadora",
      "shortName": "Fondeadora",
      "type": "mfs",
      "aliases": ""
    },
    {
      "code": "MX_20",
      "name": "Klar",
      "shortName": "Klar",
      "type": "mfs",
      "aliases": ""
    },
    {
      "code": "MX_21",
      "name": "Mercado Pago",
      "shortName": "Mercado Pago",
      "type": "mfs",
      "aliases": ""
    },
    {
      "code": "MX_22",
      "name": "Spin by Oxxo",
      "shortName": "Spin by Oxxo",
      "type": "mfs",
      "aliases": ""
    }
  ]
}