{
  "version": 1,
  "lastUpdated": "2026-05-30",
  "country": "SC",
  "institutions": [
    {
      "code": "SC_0",
      "name": "Absa Bank Seychelles",
      "shortName": "Absa Seychelles",
      "type": "bank",
      "aliases": ""
    },
    {
      "code": "SC_1",
      "name": "Al Salam Bank Seychelles",
      "shortName": "Al Salam Seychelles",
      "type": "bank",
      "aliases": ""
    },
    {
      "code": "SC_2",
      "name": "Bank of Baroda Seychelles",
      "shortName": "Bank of Baroda Seych",
      "type": "bank",
      "aliases": ""
    },
    {
      "code": "SC_3",
      "name": "Bank of Ceylon Seychelles",
      "shortName": "Bank of Ceylon Seych",
      "type": "bank",
      "aliases": ""
    },
    {
      "code": "SC_4",
      "name": "MCB Seychelles",
      "shortName": "MCB Seychelles",
      "type": "bank",
      "aliases": ""
    },
    {
      "code": "SC_5",
      "name": "Nouvobanq",
      "shortName": "Nouvobanq",
      "type": "bank",
      "aliases": ""
    },
    {
      "code": "SC_6",
      "name": "Seychelles Commercial Bank",
      "shortName": "Seychelles Commercia",
      "type": "bank",
      "aliases": ""
    },
    {
      "code": "SC_7",
      "name": "Airtel Money",
      "shortName": "Airtel Money",
      "type": "mfs",
      "aliases": ""
    }
  ]
}