{
  "version": 1,
  "lastUpdated": "2026-05-26",
  "country": "SX",
  "institutions": [
    {
      "code": "CENBSX",
      "name": "Central Bank of SX",
      "shortName": "Central Bank",
      "type": "bank",
      "aliases": ""
    },
    {
      "code": "NATBSX",
      "name": "National Bank of SX",
      "shortName": "National Bank",
      "type": "bank",
      "aliases": ""
    },
    {
      "code": "STABSX",
      "name": "State Bank of SX",
      "shortName": "State Bank",
      "type": "bank",
      "aliases": ""
    },
    {
      "code": "COBBSX",
      "name": "Commercial Bank of SX",
      "shortName": "Commercial Bank",
      "type": "bank",
      "aliases": ""
    },
    {
      "code": "FIBSX",
      "name": "First SX Bank",
      "shortName": "First Bank",
      "type": "bank",
      "aliases": ""
    }
  ]
}